{
  "groups": [
    {
      "logo": "faction_trollblood",
      "id": "faction_trollblood_warcasters",
      "entries": [],
      "label": "Warcasters"
    },
    {
      "logo": "faction_trollblood",
      "id": "faction_trollblood_warlocks",
      "entries": [
        {
          "id": "TW01",
          "type": "warlock",
          "name": "Madrak1 (Madrak Ironhide Thornwood Chieftain)",
          "cost": 29,
          "fa": "C",
          "faction": "faction_trollblood"
        },
        {
          "id": "TW02",
          "type": "warlock",
          "name": "Hoarluk1 (Hoarluk Doomshaper Shaman of the Gnarls)",
          "cost": 29,
          "fa": "C",
          "faction": "faction_trollblood"
        },
        {
          "id": "TW03",
          "type": "warlock",
          "name": "Grissel1 (Grissel Bloodsong Fell Caller)",
          "cost": 29,
          "fa": "C",
          "faction": "faction_trollblood"
        },
        {
          "id": "TW04",
          "type": "warlock",
          "name": "Grim1 (Grim Angus)",
          "cost": 29,
          "fa": "C",
          "faction": "faction_trollblood"
        },
        {
          "id": "TW05",
          "type": "warlock",
          "name": "Borka1 (Borka Kegslayer & Pyg Keg Carrier)",
          "cost": 28,
          "fa": "C",
          "faction": "faction_trollblood",
          "attachment": "TS09"
        },
        {
          "id": "TW06",
          "type": "warlock",
          "name": "Calandra (Calandra Truthsayer Oracle of the Glimmerwood)",
          "cost": 27,
          "fa": "C",
          "faction": "faction_trollblood"
        },
        {
          "id": "TW07",
          "type": "warlock",
          "name": "Gunnbjorn (Captain Gunnbjorn)",
          "cost": 28,
          "fa": "C",
          "faction": "faction_trollblood"
        },
        {
          "id": "TW08",
          "type": "warlock",
          "name": "Jarl1 (Jarl Skuld Devil of the Thornwood)",
          "cost": 30,
          "fa": "C",
          "faction": "faction_trollblood"
        },
        {
          "id": "TW09",
          "type": "warlock",
          "name": "Ragnor (Ragnor Skysplitter The Runemaster)",
          "cost": 30,
          "fa": "C",
          "faction": "faction_trollblood"
        },
        {
          "id": "TW10",
          "type": "warlock",
          "name": "Madrak2 (Madrak Ironhide World Ender)",
          "cost": 28,
          "fa": "C",
          "faction": "faction_trollblood"
        },
        {
          "id": "TW11",
          "type": "warlock",
          "name": "Hoarluk2 (Hoarluk Doomshaper Rage of Dhunia)",
          "cost": 27,
          "fa": "C",
          "faction": "faction_trollblood"
        },
        {
          "id": "TW12",
          "type": "warlock",
          "name": "Grissel2 (Grissel Bloodsong Marshal of the Kriels)",
          "cost": 27,
          "fa": "C",
          "faction": "faction_trollblood"
        },
        {
          "id": "TW13",
          "type": "warlock",
          "name": "Grim2 (Hunters Grim)",
          "cost": 25,
          "fa": "C",
          "faction": "faction_trollblood"
        },
        {
          "id": "TW15",
          "type": "warlock",
          "name": "Borka2 (Borka Vengeance of the Rimeshaws)",
          "cost": 29,
          "fa": "C",
          "faction": "faction_trollblood"
        },
        {
          "id": "TW16",
          "type": "warlock",
          "name": "Hoarluk3 (Hoarluk Doomshaper Dire Prophet & Scroll Bearers)",
          "cost": 26,
          "fa": "C",
          "faction": "faction_trollblood"
        },
        {
          "id": "TW17",
          "type": "warlock",
          "name": "Horgle2 (Horgle The Anvil)",
          "cost": 29,
          "fa": "C",
          "faction": "faction_trollblood"
        }
      ],
      "label": "Warlocks"
    },
    {
      "logo": "faction_trollblood",
      "id": "faction_trollblood_warjacks",
      "entries": [],
      "label": "Warjacks"
    },
    {
      "logo": "faction_trollblood",
      "id": "faction_trollblood_warbeasts",
      "entries": [
        {
          "id": "TB08",
          "type": "warbeast",
          "name": "Dire Troll Mauler",
          "cost": 15,
          "fa": "U",
          "faction": "faction_trollblood"
        },
        {
          "id": "TB07",
          "type": "warbeast",
          "name": "Dire Troll Blitzer",
          "cost": 16,
          "fa": "U",
          "faction": "faction_trollblood"
        },
        {
          "id": "TB03",
          "type": "warbeast",
          "name": "Troll Axer",
          "cost": 10,
          "fa": "U",
          "faction": "faction_trollblood"
        },
        {
          "id": "TB09",
          "type": "warbeast",
          "name": "Earthborn Dire Troll",
          "cost": 15,
          "fa": "U",
          "faction": "faction_trollblood"
        },
        {
          "id": "TB15",
          "type": "warbeast",
          "name": "Night Troll",
          "cost": 7,
          "fa": "U",
          "faction": "faction_trollblood"
        },
        {
          "id": "TB12",
          "type": "warbeast",
          "name": "Swamp Troll",
          "cost": 8,
          "fa": "U",
          "faction": "faction_trollblood"
        },
        {
          "id": "TB04",
          "type": "warbeast",
          "name": "Troll Bouncer",
          "cost": 9,
          "fa": "U",
          "faction": "faction_trollblood"
        },
        {
          "id": "TB18",
          "type": "warbeast",
          "name": "Glacier King",
          "cost": 35,
          "fa": "2",
          "faction": "faction_trollblood"
        },
        {
          "id": "TB01",
          "type": "warbeast",
          "name": "Pyre Troll",
          "cost": 9,
          "fa": "U",
          "faction": "faction_trollblood"
        },
        {
          "id": "TB16",
          "type": "warbeast",
          "name": "Mountain King",
          "cost": 36,
          "fa": "2",
          "faction": "faction_trollblood"
        },
        {
          "id": "TB17",
          "type": "warbeast",
          "name": "Dozer & Smigg",
          "cost": 18,
          "fa": "C",
          "faction": "faction_trollblood"
        },
        {
          "id": "TB06",
          "type": "warbeast",
          "name": "Winter Troll",
          "cost": 8,
          "fa": "U",
          "faction": "faction_trollblood"
        },
        {
          "id": "TB05",
          "type": "warbeast",
          "name": "Troll Impaler",
          "cost": 11,
          "fa": "U",
          "faction": "faction_trollblood"
        },
        {
          "id": "TB10",
          "type": "warbeast",
          "name": "Mulg the Ancient",
          "cost": 19,
          "fa": "C",
          "faction": "faction_trollblood"
        },
        {
          "id": "TB14",
          "type": "warbeast",
          "name": "Storm Troll",
          "cost": 9,
          "fa": "U",
          "faction": "faction_trollblood"
        },
        {
          "id": "TB02",
          "type": "warbeast",
          "name": "Slag Troll",
          "cost": 10,
          "fa": "U",
          "faction": "faction_trollblood"
        },
        {
          "id": "TB11",
          "type": "warbeast",
          "name": "Dire Troll Bomber",
          "cost": 19,
          "fa": "U",
          "faction": "faction_trollblood"
        },
        {
          "id": "TB13",
          "type": "warbeast",
          "name": "Rök",
          "cost": 21,
          "fa": "C",
          "faction": "faction_trollblood"
        }
      ],
      "label": "Warbeasts"
    },
    {
      "logo": "faction_trollblood",
      "id": "faction_trollblood_bes",
      "entries": [
        {
          "id": "TE01",
          "type": "battleengine",
          "name": "Trollkin War Wagon",
          "cost": 18,
          "fa": "2",
          "faction": "faction_trollblood"
        }
      ],
      "label": "Battle engines"
    },
    {
      "logo": "faction_trollblood",
      "id": "faction_trollblood_units",
      "entries": [
        {
          "id": "TU01",
          "type": "unit",
          "name": "Kriel Warriors",
          "cost": 7,
          "costMin": 7,
          "costMax": 11,
          "fa": "U",
          "min": 6,
          "max": 10,
          "faction": "faction_trollblood"
        },
        {
          "id": "TU02",
          "type": "unit",
          "name": "Krielstone Bearer & Stone Scribes",
          "cost": 6,
          "costMin": 6,
          "costMax": 9,
          "fa": "1",
          "min": 4,
          "max": 6,
          "faction": "faction_trollblood"
        },
        {
          "id": "TU03",
          "type": "unit",
          "name": "Pyg Burrowers",
          "cost": 8,
          "costMin": 8,
          "costMax": 13,
          "fa": "1",
          "min": 6,
          "max": 10,
          "faction": "faction_trollblood"
        },
        {
          "id": "TU04",
          "type": "unit",
          "name": "Pyg Bushwackers",
          "cost": 9,
          "costMin": 9,
          "costMax": 15,
          "fa": "2",
          "min": 6,
          "max": 10,
          "faction": "faction_trollblood"
        },
        {
          "id": "TU05",
          "type": "unit",
          "name": "Thumper Crew",
          "cost": 5,
          "fa": "2",
          "faction": "faction_trollblood"
        },
        {
          "id": "TU06",
          "type": "unit",
          "name": "Trollkin Champions",
          "cost": 10,
          "costMin": 10,
          "costMax": 17,
          "fa": "2",
          "min": 3,
          "max": 5,
          "faction": "faction_trollblood"
        },
        {
          "id": "TU07",
          "type": "unit",
          "name": "Trollkin Fennblades",
          "cost": 9,
          "costMin": 9,
          "costMax": 15,
          "fa": "2",
          "min": 6,
          "max": 10,
          "faction": "faction_trollblood"
        },
        {
          "id": "TU08",
          "type": "unit",
          "name": "Long Riders",
          "cost": 12,
          "costMin": 12,
          "costMax": 20,
          "fa": "2",
          "min": 3,
          "max": 5,
          "faction": "faction_trollblood"
        },
        {
          "id": "TU09",
          "type": "unit",
          "name": "Trollkin Runeshapers",
          "cost": 9,
          "fa": "3",
          "faction": "faction_trollblood"
        },
        {
          "id": "TU10",
          "type": "unit",
          "name": "Scattergunners",
          "cost": 8,
          "costMin": 8,
          "costMax": 14,
          "fa": "3",
          "min": 6,
          "max": 10,
          "faction": "faction_trollblood"
        },
        {
          "id": "TU11",
          "type": "unit",
          "name": "Trollkin Scouts",
          "cost": 10,
          "fa": "2",
          "faction": "faction_trollblood"
        },
        {
          "id": "TU12",
          "type": "unit",
          "name": "Trollkin Sluggers",
          "cost": 8,
          "costMin": 8,
          "costMax": 13,
          "fa": "2",
          "min": 3,
          "max": 5,
          "faction": "faction_trollblood"
        },
        {
          "id": "TU13",
          "type": "unit",
          "name": "Sons of Bragg",
          "cost": 11,
          "fa": "C",
          "faction": "faction_trollblood"
        },
        {
          "id": "TU14",
          "type": "unit",
          "name": "Trollkin Warders",
          "cost": 10,
          "costMin": 10,
          "costMax": 17,
          "fa": "2",
          "min": 3,
          "max": 5,
          "faction": "faction_trollblood"
        },
        {
          "id": "TU15",
          "type": "unit",
          "name": "Northkin Fire Eaters",
          "cost": 7,
          "fa": "2",
          "faction": "faction_trollblood"
        },
        {
          "id": "TU16",
          "type": "unit",
          "name": "Trollkin Highwaymen",
          "cost": 9,
          "costMin": 9,
          "costMax": 15,
          "fa": "2",
          "min": 6,
          "max": 10,
          "faction": "faction_trollblood"
        },
        {
          "id": "TU18",
          "type": "unit",
          "name": "Pummeler Crew",
          "cost": 6,
          "fa": "2",
          "faction": "faction_trollblood"
        },
        {
          "id": "TU17",
          "type": "unit",
          "name": "Dhunian Knot",
          "cost": 6,
          "fa": "2",
          "faction": "faction_trollblood"
        }
      ],
      "label": "Units"
    },
    {
      "logo": "faction_trollblood",
      "id": "faction_trollblood_UAs",
      "entries": [
        {
          "id": "TA05",
          "type": "UA",
          "name": "Skaldi Bonehammer",
          "cost": 5,
          "fa": "C",
          "faction": "faction_trollblood",
          "restricted_to": "TU06"
        },
        {
          "id": "TA03",
          "type": "UA",
          "name": "Stone Scribe Elder",
          "cost": 3,
          "fa": "1",
          "faction": "faction_trollblood",
          "restricted_to": "TU02"
        },
        {
          "id": "TA07",
          "type": "UA",
          "name": "Pyg Bushwhacker Officer & Mortar",
          "cost": 5,
          "fa": "2",
          "faction": "faction_trollblood",
          "restricted_to": "TU04"
        },
        {
          "id": "TA04",
          "type": "UA",
          "name": "Trollkin Fennblade Officer & Drummer",
          "cost": 5,
          "fa": "2",
          "faction": "faction_trollblood",
          "restricted_to": "TU07"
        },
        {
          "id": "TA06",
          "type": "UA",
          "name": "Scattergunner Officer & Standard",
          "cost": 4,
          "fa": "3",
          "faction": "faction_trollblood",
          "restricted_to": "TU10"
        },
        {
          "id": "TA01",
          "type": "UA",
          "name": "Kriel Warrior Standard Bearer & Piper",
          "cost": 3,
          "fa": "U",
          "faction": "faction_trollblood",
          "restricted_to": "TU01"
        }
      ],
      "label": "Unit Attachments"
    },
    {
      "logo": "faction_trollblood",
      "id": "faction_trollblood_WAs",
      "entries": [
        {
          "id": "TA08",
          "type": "WA",
          "name": "Trollkin Sorcerer",
          "cost": 3,
          "fa": "U",
          "faction": "faction_trollblood",
          "restricted_to": [
            "TU01",
            "TU02",
            "TU05",
            "TU06",
            "TU07",
            "TU09",
            "TU10",
            "TU11",
            "TU12",
            "TU13",
            "TU14",
            "TU15",
            "TU16",
            "TU17",
            "TU18"
          ],
          "max_attach": 3
        },
        {
          "id": "TA02",
          "type": "WA",
          "name": "Kriel Warrior Caber Thrower",
          "cost": 2,
          "fa": "U",
          "faction": "faction_trollblood",
          "restricted_to": "TU01",
          "max_attach": 3
        }
      ],
      "label": "Weapon Attachments"
    },
    {
      "logo": "faction_trollblood",
      "id": "faction_trollblood_solos",
      "entries": [
        {
          "id": "TS01",
          "type": "solo",
          "name": "Fell Caller Hero",
          "cost": 5,
          "fa": "2",
          "faction": "faction_trollblood"
        },
        {
          "id": "TS02",
          "type": "solo",
          "name": "Stone Scribe Chronicler",
          "cost": 4,
          "fa": "2",
          "faction": "faction_trollblood"
        },
        {
          "id": "TS03",
          "type": "solo",
          "name": "Troll Whelps",
          "cost": 4,
          "fa": "3",
          "faction": "faction_trollblood"
        },
        {
          "id": "TS04",
          "type": "solo",
          "name": "Trollkin Champion Hero",
          "cost": 5,
          "fa": "2",
          "faction": "faction_trollblood"
        },
        {
          "id": "TS05",
          "type": "solo",
          "name": "Horthol Long Rider Hero",
          "cost": 8,
          "fa": "C",
          "faction": "faction_trollblood"
        },
        {
          "id": "TS06",
          "type": "soloAttachment",
          "name": "Trollkin Runebearer",
          "cost": 4,
          "fa": "1",
          "faction": "faction_trollblood"
        },
        {
          "id": "TS07",
          "type": "solo",
          "name": "Trollblood Skinner",
          "cost": 4,
          "fa": "2",
          "faction": "faction_trollblood"
        },
        {
          "id": "TS08",
          "type": "solo",
          "name": "Janissa Stonetide",
          "cost": 4,
          "fa": "C",
          "faction": "faction_trollblood"
        },
        {
          "id": "TS10",
          "type": "solo",
          "name": "Fennblade Kithkar",
          "cost": 4,
          "fa": "2",
          "faction": "faction_trollblood"
        },
        {
          "id": "TS11",
          "type": "soloLesserWarlock",
          "name": "Horgle Ironstrike",
          "cost": 4,
          "fa": "C",
          "faction": "faction_trollblood",
          "restricted_to": [
            "TB01",
            "TB02"
          ]
        },
        {
          "id": "TS12",
          "type": "solo",
          "name": "Braylen Wanderheart",
          "cost": 5,
          "fa": "C",
          "faction": "faction_trollblood"
        },
        {
          "id": "TS09",
          "type": "soloAttachment",
          "name": "Keg Carrier",
          "cost": 0,
          "fa": "C",
          "faction": "faction_trollblood",
          "restricted_to": "TW05"
        },
        {
          "id": "TS14",
          "type": "solo",
          "name": "Northkin Shaman",
          "cost": 4,
          "fa": "2",
          "faction": "faction_trollblood"
        }
      ],
      "label": "Solos"
    }
  ],
  "tiers": []
}
